shiftmemory/__init__.py
shiftmemory/exceptions.py
shiftmemory/memory.py
shiftmemory/times.py
shiftmemory/adapter/__init__.py
shiftmemory/adapter/dummy.py
shiftmemory/adapter/redis.py
shiftmemory/cli/__init__.py
shiftmemory/cli/console.py
shiftmemory-0.0.8.dist-info/LICENSE.txt
shiftmemory-0.0.8.dist-info/METADATA
shiftmemory-0.0.8.dist-info/WHEEL
shiftmemory-0.0.8.dist-info/entry_points.txt
shiftmemory-0.0.8.dist-info/top_level.txt
shiftmemory-0.0.8.dist-info/RECORD
